nonebot_plugin_access_control_api/__init__.py
nonebot_plugin_access_control_api/context.py
nonebot_plugin_access_control_api/errors.py
nonebot_plugin_access_control_api/event_bus.py
nonebot_plugin_access_control_api/models/__init__.py
nonebot_plugin_access_control_api/models/permission.py
nonebot_plugin_access_control_api/models/rate_limit.py
nonebot_plugin_access_control_api/service/__init__.py
nonebot_plugin_access_control_api/service/_dummy/__init__.py
nonebot_plugin_access_control_api/service/_dummy/factory.py
nonebot_plugin_access_control_api/service/_dummy/patcher.py
nonebot_plugin_access_control_api/service/_dummy/permission.py
nonebot_plugin_access_control_api/service/_dummy/rate_limit.py
nonebot_plugin_access_control_api/service/contextvars.py
nonebot_plugin_access_control_api/service/interface/__init__.py
nonebot_plugin_access_control_api/service/interface/factory.py
nonebot_plugin_access_control_api/service/interface/nonebot_service.py
nonebot_plugin_access_control_api/service/interface/patcher.py
nonebot_plugin_access_control_api/service/interface/permission.py
nonebot_plugin_access_control_api/service/interface/plugin_service.py
nonebot_plugin_access_control_api/service/interface/rate_limit.py
nonebot_plugin_access_control_api/service/interface/service.py
nonebot_plugin_access_control_api/service/interface/service_base.py
nonebot_plugin_access_control_api/service/interface/subservice.py
nonebot_plugin_access_control_api/service/interface/subservice_owner.py
nonebot_plugin_access_control_api/service/methods.py
nonebot_plugin_access_control_api/service/nonebot_service.py
nonebot_plugin_access_control_api/service/plugin_service.py
nonebot_plugin_access_control_api/service/service.py
nonebot_plugin_access_control_api/service/subservice.py
nonebot_plugin_access_control_api/service/subservice_owner.py
nonebot_plugin_access_control_api/subject/__init__.py
nonebot_plugin_access_control_api/subject/extractor/__init__.py
nonebot_plugin_access_control_api-1.2.1.dist-info/LICENSE
nonebot_plugin_access_control_api-1.2.1.dist-info/METADATA
nonebot_plugin_access_control_api-1.2.1.dist-info/WHEEL
nonebot_plugin_access_control_api-1.2.1.dist-info/RECORD
