Metadata-Version: 2.3
Name: nonebot-plugin-access-control-api
Version: 1.2.1
Summary: 
License: MIT
Author: ssttkkl
Author-email: huang.wen.long@hotmail.com
Requires-Python: >=3.8,<4.0
Classifier: License :: OSI Approved :: MIT License
Classifier: Programming Language :: Python :: 3
Classifier: Programming Language :: Python :: 3.8
Classifier: Programming Language :: Python :: 3.9
Classifier: Programming Language :: Python :: 3.10
Classifier: Programming Language :: Python :: 3.11
Classifier: Programming Language :: Python :: 3.12
Classifier: Programming Language :: Python :: 3.13
Requires-Dist: nonebot2 (>=2.2.0,<3.0.0)
Project-URL: Repository, https://github.com/bot-ssttkkl/nonebot-plugin-access-control
